chapter_converter/__init__.py
chapter_converter/__main__.py
chapter_converter/chapter_converter.py
chapter_converter/gui.py
chapter_converter-1.2.1.dist-info/LICENSE
chapter_converter-1.2.1.dist-info/METADATA
chapter_converter-1.2.1.dist-info/WHEEL
chapter_converter-1.2.1.dist-info/entry_points.txt
chapter_converter-1.2.1.dist-info/top_level.txt
chapter_converter-1.2.1.dist-info/RECORD
