Metadata-Version: 2.1
Name: chapter-converter
Version: 1.2.1
Summary: Convert between several different video chapter file formats with ease.
Home-page: https://github.com/fireattack/chapter_converter
Author: fireattack
Author-email: 
License: MIT
Project-URL: Source, https://github.com/fireattack/chapter_converter
Project-URL: Tracker, https://github.com/fireattack/chapter_converter/issues
Requires-Python: >=3.7
License-File: LICENSE
Requires-Dist: chardet
Requires-Dist: pyperclip
